[
{
    "title": "X",
    "alt_title": "",
    "kvikmyndir_is_id": 14222,
    "release_year": 2022,
    "poster_url": "https://kvikmyndir.is/images/poster/14222_500.jpg",
    "content_rating_in_years": 16,
    "scrape_url": "https://kvikmyndir.is/mynd/?id=14222",
    "description": "Flugbeitt hrollvekja sem farið hefur sigurför um heiminn og hlotið mikið lof áhorfenda og gagnrýnenda. 'X' er óður til sígildra hryllingsmynda og segir frá hópi ungra kvikmyndagerðarmanna sem vinnur að gerð klámmyndar úti á landi í Texas árið 1979. Framleiðslan mætir hins vegar óvæntum hindrunum þegar gestgjafi þeirra stendur þá að verki. Þá lendir...",
    "genres": [
        "Hrollvekja",
        "Spennutryllir",
        "Ráðgáta"
    ],
    "duration_in_mins": 105,
    "rating_urls": [
        "http://imdb.com/title/tt13560574",
        "https://www.themoviedb.org/tv/760104",
        "https://www.rottentomatoes.com/m/x_2022"
    ],
    "language": "Enska",
    "image_urls": [
        "https://kvikmyndir.is/images/poster/14222_500.jpg"
    ],
    "showtimes": [
        {
            "time": "2023-08-08T22:00:00",
            "cinema": "Bíó Paradís",
            "purchase_url": "https://tickets.bioparadis.is/#book/3110",
            "hall": "Salur 3",
            "tags": []
        }
    ],
    "trailer_url": "https://www.youtube.com/watch?v=Awg3cWuHfoc",
    "images": [
        {
            "url": "https://kvikmyndir.is/images/poster/14222_500.jpg",
            "path": "full/c8c0a34e8f18eb510946456af859ffb311f1e263.jpg",
            "checksum": "84fa23aa045074e8110b38c5e104f5ae",
            "status": "downloaded"
        }
    ]
},
{
    "title": "Barbie",
    "alt_title": "",
    "kvikmyndir_is_id": 15054,
    "release_year": 2023,
    "poster_url": "https://kvikmyndir.is/images/poster/15054_500.jpg",
    "content_rating_in_years": 16,
    "scrape_url": "https://kvikmyndir.is/mynd/?id=15054",
    "description": "Barbie og Ken njóta lífsins í Barbie landi, hinum litríka og fullkomna heimi. En þegar þau fá tækifæri til að fara yfir í hina raunverulegu veröld uppgötva þau fljótt bæði gleðina og hætturnar sem felast í því að búa á meðal manna.",
    "genres": [
        "Gaman",
        "Ævintýri"
    ],
    "duration_in_mins": 114,
    "rating_urls": [
        "http://imdb.com/title/tt1517268",
        "https://www.rottentomatoes.com/m/barbie"
    ],
    "language": "Enska",
    "image_urls": [
        "https://kvikmyndir.is/images/poster/15054_500.jpg"
    ],
    "showtimes": [
        {
            "time": "2023-08-08T12:30:00",
            "cinema": "Sambíóin Kringlunni",
            "purchase_url": "http://www.sambio.is/websales/show/363665/",
            "hall": "Salur 1",
            "tags": []
        },
        {
            "time": "2023-08-08T15:00:00",
            "cinema": "Sambíóin Kringlunni",
            "purchase_url": "http://www.sambio.is/websales/show/363666/",
            "hall": "Salur 1",
            "tags": []
        },
        {
            "time": "2023-08-08T18:20:00",
            "cinema": "Sambíóin Kringlunni",
            "purchase_url": "http://www.sambio.is/websales/show/363856/",
            "hall": "Ásberg",
            "tags": []
        },
        {
            "time": "2023-08-08T18:30:00",
            "cinema": "Sambíóin Kringlunni",
            "purchase_url": "http://www.sambio.is/websales/show/363667/",
            "hall": "Salur 1",
            "tags": []
        },
        {
            "time": "2023-08-08T21:30:00",
            "cinema": "Sambíóin Kringlunni",
            "purchase_url": "http://www.sambio.is/websales/show/363721/",
            "hall": "Salur 2",
            "tags": []
        },
        {
            "time": "2023-08-08T13:00:00",
            "cinema": "Sambíóin Álfabakka",
            "purchase_url": "http://www.sambio.is/websales/show/363553/",
            "hall": "Salur 2",
            "tags": []
        },
        {
            "time": "2023-08-08T13:00:00",
            "cinema": "Sambíóin Álfabakka",
            "purchase_url": "http://www.sambio.is/websales/show/363643/",
            "hall": "Lúxus VIP",
            "tags": []
        },
        {
            "time": "2023-08-08T14:00:00",
            "cinema": "Sambíóin Álfabakka",
            "purchase_url": "http://www.sambio.is/websales/show/363613/",
            "hall": "Salur 3",
            "tags": []
        },
        {
            "time": "2023-08-08T15:00:00",
            "cinema": "Sambíóin Álfabakka",
            "purchase_url": "http://www.sambio.is/websales/show/363584/",
            "hall": "Salur 1",
            "tags": []
        },
        {
            "time": "2023-08-08T16:00:00",
            "cinema": "Sambíóin Álfabakka",
            "purchase_url": "http://www.sambio.is/websales/show/363644/",
            "hall": "Lúxus VIP",
            "tags": []
        },
        {
            "time": "2023-08-08T16:30:00",
            "cinema": "Sambíóin Álfabakka",
            "purchase_url": "http://www.sambio.is/websales/show/363614/",
            "hall": "Salur 3",
            "tags": []
        },
        {
            "time": "2023-08-08T17:30:00",
            "cinema": "Sambíóin Álfabakka",
            "purchase_url": "http://www.sambio.is/websales/show/363585/",
            "hall": "Salur 1",
            "tags": []
        },
        {
            "time": "2023-08-08T20:00:00",
            "cinema": "Sambíóin Álfabakka",
            "purchase_url": "http://www.sambio.is/websales/show/363586/",
            "hall": "Salur 1",
            "tags": []
        },
        {
            "time": "2023-08-08T22:00:00",
            "cinema": "Sambíóin Álfabakka",
            "purchase_url": "http://www.sambio.is/websales/show/363806/",
            "hall": "Lúxus VIP",
            "tags": []
        },
        {
            "time": "2023-08-08T22:30:00",
            "cinema": "Sambíóin Álfabakka",
            "purchase_url": "http://www.sambio.is/websales/show/363587/",
            "hall": "Salur 1",
            "tags": []
        },
        {
            "time": "2023-08-08T13:40:00",
            "cinema": "Smárabíó",
            "purchase_url": "https://sala.smarabio.is/Ticketing/visSelectTickets.aspx?cinemacode=002&txtSessionId=100933&visLang=1",
            "hall": "LÚXUS",
            "tags": [
                "LÚX"
            ]
        },
        {
            "time": "2023-08-08T14:00:00",
            "cinema": "Smárabíó",
            "purchase_url": "https://sala.smarabio.is/Ticketing/visSelectTickets.aspx?cinemacode=002&txtSessionId=100932&visLang=1",
            "hall": "MAX",
            "tags": []
        },
        {
            "time": "2023-08-08T16:20:00",
            "cinema": "Smárabíó",
            "purchase_url": "https://sala.smarabio.is/Ticketing/visSelectTickets.aspx?cinemacode=002&txtSessionId=100984&visLang=1",
            "hall": "LÚXUS",
            "tags": [
                "LÚX"
            ]
        },
        {
            "time": "2023-08-08T16:40:00",
            "cinema": "Smárabíó",
            "purchase_url": "https://sala.smarabio.is/Ticketing/visSelectTickets.aspx?cinemacode=002&txtSessionId=100936&visLang=1",
            "hall": "MAX",
            "tags": []
        },
        {
            "time": "2023-08-08T19:00:00",
            "cinema": "Smárabíó",
            "purchase_url": "https://sala.smarabio.is/Ticketing/visSelectTickets.aspx?cinemacode=002&txtSessionId=100926&visLang=1",
            "hall": "LÚXUS",
            "tags": [
                "LÚX"
            ]
        },
        {
            "time": "2023-08-08T19:20:00",
            "cinema": "Smárabíó",
            "purchase_url": "https://sala.smarabio.is/Ticketing/visSelectTickets.aspx?cinemacode=002&txtSessionId=100945&visLang=1",
            "hall": "MAX",
            "tags": []
        },
        {
            "time": "2023-08-08T22:10:00",
            "cinema": "Smárabíó",
            "purchase_url": "https://sala.smarabio.is/Ticketing/visSelectTickets.aspx?cinemacode=002&txtSessionId=100940&visLang=1",
            "hall": "Salur 4",
            "tags": []
        },
        {
            "time": "2023-08-08T15:00:00",
            "cinema": "Sambíóin Egilshöll",
            "purchase_url": "http://www.sambio.is/websales/show/363920/",
            "hall": "Salur 1",
            "tags": []
        },
        {
            "time": "2023-08-08T17:30:00",
            "cinema": "Sambíóin Egilshöll",
            "purchase_url": "http://www.sambio.is/websales/show/363921/",
            "hall": "Salur 1",
            "tags": []
        },
        {
            "time": "2023-08-08T20:00:00",
            "cinema": "Sambíóin Egilshöll",
            "purchase_url": "http://www.sambio.is/websales/show/363469/",
            "hall": "Salur 1",
            "tags": []
        },
        {
            "time": "2023-08-08T21:00:00",
            "cinema": "Sambíóin Egilshöll",
            "purchase_url": "http://www.sambio.is/websales/show/363934/",
            "hall": "Salur 3",
            "tags": []
        },
        {
            "time": "2023-08-08T22:20:00",
            "cinema": "Sambíóin Egilshöll",
            "purchase_url": "http://www.sambio.is/websales/show/363922/",
            "hall": "Salur 1",
            "tags": []
        },
        {
            "time": "2023-08-08T16:00:00",
            "cinema": "Sambíóin Akureyri",
            "purchase_url": "http://www.sambio.is/websales/show/363952/",
            "hall": "Salur 1",
            "tags": []
        },
        {
            "time": "2023-08-08T18:30:00",
            "cinema": "Sambíóin Akureyri",
            "purchase_url": "http://www.sambio.is/websales/show/363953/",
            "hall": "Salur 1",
            "tags": []
        },
        {
            "time": "2023-08-08T21:00:00",
            "cinema": "Sambíóin Akureyri",
            "purchase_url": "http://www.sambio.is/websales/show/363954/",
            "hall": "Salur 1",
            "tags": []
        },
        {
            "time": "2023-08-08T17:30:00",
            "cinema": "Sambíóin Keflavík",
            "purchase_url": "http://www.sambio.is/websales/show/363248/",
            "hall": "Salur 1",
            "tags": []
        }
    ],
    "trailer_url": "https://www.youtube.com/watch?v=pBk4NYhWNMM",
    "images": [
        {
            "url": "https://kvikmyndir.is/images/poster/15054_500.jpg",
            "path": "full/84f8b73c4fbdd5c1b46d613bade1e980c760e509.jpg",
            "checksum": "d8e23e40b01f01f4775eedcf90ec89b6",
            "status": "downloaded"
        }
    ]
},
{
    "title": "Hit Big",
    "alt_title": "Hetki lyö",
    "kvikmyndir_is_id": 16292,
    "release_year": 2022,
    "poster_url": "https://kvikmyndir.is/images/poster/16292_500.jpg",
    "content_rating_in_years": 16,
    "scrape_url": "https://kvikmyndir.is/mynd/?id=16292",
    "description": "Marjaleena er 60 ára fyrrum fegurðardrottning og drykkjusvoli. Hún kemst að því að eiginmaður hennar er með óhreint mjöl í pokahorninu því hann ráðgerir glæpsamlegt athæfi eftir lausn úr fangelsi. Hún ákveður að taka til sinna ráða því hún ætlar að ná í sinn skerf af peningunum sem um ræðir. Hún ætlar ekki að láta vaða yfir sig á skítugum...",
    "genres": [
        "Gaman",
        "Drama",
        "Glæpa"
    ],
    "duration_in_mins": 123,
    "rating_urls": [
        "http://imdb.com/title/tt17716526"
    ],
    "language": "Finnska",
    "image_urls": [
        "https://kvikmyndir.is/images/poster/16292_500.jpg"
    ],
    "showtimes": [
        {
            "time": "2023-08-08T18:45:00",
            "cinema": "Bíó Paradís",
            "purchase_url": "https://tickets.bioparadis.is/#book/3094",
            "hall": "Salur 2",
            "tags": []
        }
    ],
    "trailer_url": "https://www.youtube.com/watch?v=Z1rfFiOnamg",
    "images": [
        {
            "url": "https://kvikmyndir.is/images/poster/16292_500.jpg",
            "path": "full/91e59c395deb119d4dc453a98461f3e18189d8a7.jpg",
            "checksum": "943c7943e05260b91cd9eb626aea5158",
            "status": "downloaded"
        }
    ]
},
{
    "title": "Mission: Impossible - Dead Reckoning - Part One",
    "alt_title": "",
    "kvikmyndir_is_id": 13420,
    "release_year": 2023,
    "poster_url": "https://kvikmyndir.is/images/poster/13420_500.jpg",
    "content_rating_in_years": 12,
    "scrape_url": "https://kvikmyndir.is/mynd/?id=13420",
    "description": "Ethan Hunt og félagar í Mission Impossible hópnum þurfa að finna lykilinn að stórhættulegu vopni sem ógnar öllu mannkyni áður en hann lendir í röngum höndum. Nú hefst hættulegur eltingarleikur sem teygir sig víða um lönd. Dularfullur en mjög valdamikill óvinur birtist og Ethan þarf að hugleiða hvort verkefnið sé mikilvægara en líf þeirra sem honum þykir...",
    "genres": [
        "Spenna",
        "Spennutryllir",
        "Ævintýri"
    ],
    "duration_in_mins": 163,
    "rating_urls": [
        "http://imdb.com/title/tt9603212",
        "https://www.rottentomatoes.com/m/mission_impossible_dead_reckoning_part_one"
    ],
    "language": "Enska",
    "image_urls": [
        "https://kvikmyndir.is/images/poster/13420_500.jpg"
    ],
    "showtimes": [
        {
            "time": "2023-08-08T14:40:00",
            "cinema": "Sambíóin Kringlunni",
            "purchase_url": "http://www.sambio.is/websales/show/363691/",
            "hall": "Salur 3",
            "tags": []
        },
        {
            "time": "2023-08-08T18:00:00",
            "cinema": "Sambíóin Kringlunni",
            "purchase_url": "http://www.sambio.is/websales/show/364024/",
            "hall": "Salur 3",
            "tags": []
        },
        {
            "time": "2023-08-08T15:00:00",
            "cinema": "Sambíóin Egilshöll",
            "purchase_url": "http://www.sambio.is/websales/show/363935/",
            "hall": "Salur 3",
            "tags": []
        },
        {
            "time": "2023-08-08T17:40:00",
            "cinema": "Sambíóin Egilshöll",
            "purchase_url": "http://www.sambio.is/websales/show/363941/",
            "hall": "Salur 4",
            "tags": []
        },
        {
            "time": "2023-08-08T15:40:00",
            "cinema": "Sambíóin Álfabakka",
            "purchase_url": "http://www.sambio.is/websales/show/363550/",
            "hall": "Salur 2",
            "tags": []
        },
        {
            "time": "2023-08-08T18:40:00",
            "cinema": "Sambíóin Álfabakka",
            "purchase_url": "http://www.sambio.is/websales/show/363641/",
            "hall": "Lúxus VIP",
            "tags": []
        },
        {
            "time": "2023-08-08T19:00:00",
            "cinema": "Sambíóin Álfabakka",
            "purchase_url": "http://www.sambio.is/websales/show/363551/",
            "hall": "Salur 2",
            "tags": []
        },
        {
            "time": "2023-08-08T22:20:00",
            "cinema": "Sambíóin Álfabakka",
            "purchase_url": "http://www.sambio.is/websales/show/363552/",
            "hall": "Salur 2",
            "tags": []
        },
        {
            "time": "2023-08-08T17:45:00",
            "cinema": "Laugarásbíó",
            "purchase_url": "http://kvikmyndahusio.azurewebsites.net/websales/show/769760/",
            "hall": "Salur B",
            "tags": []
        },
        {
            "time": "2023-08-08T21:00:00",
            "cinema": "Laugarásbíó",
            "purchase_url": "http://kvikmyndahusio.azurewebsites.net/websales/show/769761/",
            "hall": "Salur B",
            "tags": []
        },
        {
            "time": "2023-08-08T19:00:00",
            "cinema": "Smárabíó",
            "purchase_url": "https://sala.smarabio.is/Ticketing/visSelectTickets.aspx?cinemacode=002&txtSessionId=100927&visLang=1",
            "hall": "Salur 5",
            "tags": []
        }
    ],
    "trailer_url": "https://www.youtube.com/watch?v=2m1drlOZSDw",
    "images": [
        {
            "url": "https://kvikmyndir.is/images/poster/13420_500.jpg",
            "path": "full/e28f59afd4ad5969cd029e6033b266f9e5dff8a0.jpg",
            "checksum": "9b3c9e1eaa6dd583461c2940dd2d2386",
            "status": "downloaded"
        }
    ]
},
{
    "title": "Kysset",
    "alt_title": "Kossinn",
    "kvikmyndir_is_id": 16161,
    "release_year": 2022,
    "poster_url": "https://kvikmyndir.is/images/poster/16161_500.jpg",
    "content_rating_in_years": 16,
    "scrape_url": "https://kvikmyndir.is/mynd/?id=16161",
    "description": "Myndin fylgir Antoni sem hefur það helsta markmið að klára þjálfun sína í riddaraliðinu. Á meðan á þjálfuninni stendur skipar hann sveitinni sinni að hjálpa auðmanni úr klípu og hittir í kjölfarið Edith dóttur hans sem lenti í slysi.",
    "genres": [
        "Rómantík",
        "Drama"
    ],
    "duration_in_mins": 116,
    "rating_urls": [
        "http://imdb.com/title/tt15822942"
    ],
    "language": "Danska",
    "image_urls": [
        "https://kvikmyndir.is/images/poster/16161_500.jpg"
    ],
    "showtimes": [
        {
            "time": "2023-08-08T19:00:00",
            "cinema": "Bíó Paradís",
            "purchase_url": "https://tickets.bioparadis.is/#book/3098",
            "hall": "Salur 3",
            "tags": []
        }
    ],
    "trailer_url": "https://www.youtube.com/watch?v=gkTdXrPWJsg",
    "images": [
        {
            "url": "https://kvikmyndir.is/images/poster/16161_500.jpg",
            "path": "full/ad54988aa5fe44ed40c0cdf1c6386cc70194207f.jpg",
            "checksum": "1db784ea0d25e2549c4488bd32a73955",
            "status": "downloaded"
        }
    ]
},
{
    "title": "Meet Me in the Bathroom",
    "alt_title": "",
    "kvikmyndir_is_id": 16338,
    "release_year": 2022,
    "poster_url": "https://kvikmyndir.is/images/poster/16338_500.jpg",
    "content_rating_in_years": 16,
    "scrape_url": "https://kvikmyndir.is/mynd/?id=16338",
    "description": "Yfirgripsmikið ferðalag um tónlistarsenuna í New York, heimildarmynd sem fjallar um sprengingu í uppgangi indie hljómsveita í kringum aldamótin 2000. Hljómsveitir á borð við The Strokes, The Moldy Peaches, Yeah Yeah Yeahs og Interpol stálu senunni.",
    "genres": [
        "Tónlist",
        "Heimildarmynd"
    ],
    "duration_in_mins": 105,
    "rating_urls": [
        "https://www.rottentomatoes.com/m/meet_me_in_the_bathroom",
        "http://imdb.com/title/tt16378298"
    ],
    "language": "Enska",
    "image_urls": [
        "https://kvikmyndir.is/images/poster/16338_500.jpg"
    ],
    "showtimes": [
        {
            "time": "2023-08-08T21:00:00",
            "cinema": "Bíó Paradís",
            "purchase_url": "https://tickets.bioparadis.is/#book/3080",
            "hall": "Salur 1",
            "tags": []
        }
    ],
    "trailer_url": "https://www.youtube.com/watch?v=UgHN-YE7IPI",
    "images": [
        {
            "url": "https://kvikmyndir.is/images/poster/16338_500.jpg",
            "path": "full/4c126497b9f8e3ca741f30381270b7badd71e4be.jpg",
            "checksum": "edd766ac7be3acd2d5d943aa373752d1",
            "status": "downloaded"
        }
    ]
},
{
    "title": "Fædre og mødre",
    "alt_title": "Feður og mæður",
    "kvikmyndir_is_id": 16166,
    "release_year": 2022,
    "poster_url": "https://kvikmyndir.is/images/poster/16166_500.jpg",
    "content_rating_in_years": 0,
    "scrape_url": "https://kvikmyndir.is/mynd/?id=16166",
    "description": "Hér er fjallað um hjónin Piv og Ulrik sem þurfa að feta sig í gegnum stigveldi, samkeppni og duldar áætlanir í nýja skóla dóttur sinnar, meðal annars í vinsælli útilegu skólans.",
    "genres": [
        "Gaman",
        "Drama"
    ],
    "duration_in_mins": 97,
    "rating_urls": [
        "http://imdb.com/title/tt15964414"
    ],
    "language": "Danska",
    "image_urls": [
        "https://kvikmyndir.is/images/poster/16166_500.jpg"
    ],
    "showtimes": [
        {
            "time": "2023-08-08T16:45:00",
            "cinema": "Bíó Paradís",
            "purchase_url": "https://tickets.bioparadis.is/#book/3093",
            "hall": "Salur 2",
            "tags": []
        }
    ],
    "trailer_url": "https://www.youtube.com/watch?v=rfII6uPjUUA",
    "images": [
        {
            "url": "https://kvikmyndir.is/images/poster/16166_500.jpg",
            "path": "full/c960ca9e737fe3144f8574d30215f10147d516f5.jpg",
            "checksum": "39e3a919a082aacc875550284e5ff75e",
            "status": "downloaded"
        }
    ]
},
{
    "title": "Close",
    "alt_title": "",
    "kvikmyndir_is_id": 14992,
    "release_year": 2022,
    "poster_url": "https://kvikmyndir.is/images/poster/14992_500.jpg",
    "content_rating_in_years": 12,
    "scrape_url": "https://kvikmyndir.is/mynd/?id=14992",
    "description": "Innileg vinátta tveggja 13 ára drengja, Remí og Léo, er rofin án fyrirvara. Léó leitar skýringa og snýr sér að móður Remí til að reyna að skilja hvað gerðist.",
    "genres": [
        "Drama"
    ],
    "duration_in_mins": 105,
    "rating_urls": [
        "http://imdb.com/title/tt9660502",
        "https://www.rottentomatoes.com/m/close_2022"
    ],
    "language": "Hollenska",
    "image_urls": [
        "https://kvikmyndir.is/images/poster/14992_500.jpg"
    ],
    "showtimes": [
        {
            "time": "2023-08-08T21:15:00",
            "cinema": "Bíó Paradís",
            "purchase_url": "https://tickets.bioparadis.is/#book/3095",
            "hall": "Salur 2",
            "tags": []
        }
    ],
    "trailer_url": "https://www.youtube.com/watch?v=-T12kvsAfjk",
    "images": [
        {
            "url": "https://kvikmyndir.is/images/poster/14992_500.jpg",
            "path": "full/067a3c380f5443d0983e46c0686935d23fd102cc.jpg",
            "checksum": "44ef83dbdb6f80875c8638825ae9fca3",
            "status": "downloaded"
        }
    ]
},
{
    "title": "Asteroid City",
    "alt_title": "",
    "kvikmyndir_is_id": 16090,
    "release_year": 2023,
    "poster_url": "https://kvikmyndir.is/images/poster/16090_500.jpg",
    "content_rating_in_years": 12,
    "scrape_url": "https://kvikmyndir.is/mynd/?id=16090",
    "description": "Myndin gerist í skálduðum bandarískum eyðimerkurbæ árið 1955. Dagskrá stjörnuskoðunarráðstefnu unglinga fær óvænta truflun af heimssögulegum atburðum.",
    "genres": [
        "Gaman",
        "Rómantík"
    ],
    "duration_in_mins": 104,
    "rating_urls": [
        "http://imdb.com/title/tt14230388",
        "https://www.rottentomatoes.com/m/asteroid_city"
    ],
    "language": "Enska",
    "image_urls": [
        "https://kvikmyndir.is/images/poster/16090_500.jpg"
    ],
    "showtimes": [
        {
            "time": "2023-08-08T16:45:00",
            "cinema": "Bíó Paradís",
            "purchase_url": "https://tickets.bioparadis.is/#book/3079",
            "hall": "Salur 1",
            "tags": []
        },
        {
            "time": "2023-08-08T18:50:00",
            "cinema": "Bíó Paradís",
            "purchase_url": "https://tickets.bioparadis.is/#book/3077",
            "hall": "Salur 1",
            "tags": []
        }
    ],
    "trailer_url": "https://www.youtube.com/watch?v=9FXCSXuGTF4",
    "images": [
        {
            "url": "https://kvikmyndir.is/images/poster/16090_500.jpg",
            "path": "full/fe02bf23b5af26c4378cf315842a398e5eb1ddc0.jpg",
            "checksum": "cea3ab25675e749453219a403b63c09f",
            "status": "downloaded"
        }
    ]
},
{
    "title": "Á ferð með mömmu",
    "alt_title": "Driving Mum",
    "kvikmyndir_is_id": 15003,
    "release_year": 2022,
    "poster_url": "https://kvikmyndir.is/images/poster/gqtl0yocuxqdqzbfiz6ofa0yfdg-1669500619.jpg",
    "content_rating_in_years": 16,
    "scrape_url": "https://kvikmyndir.is/mynd/?id=15003",
    "description": "Þegar móðir Jóns og hans mesti áhrifavaldur fellur frá verða alger umskipti í lífi hans. Með uppáklætt líkið í aftursætinu og hundinn Brésnef við hlið sér tekst hann á hendur ferð þvert yfir landið til að heiðra hennar síðustu ósk. En mamma hefur ekki sagt sitt síðasta.",
    "genres": [
        "Gaman",
        "Drama",
        "Íslensk mynd"
    ],
    "duration_in_mins": 112,
    "rating_urls": [
        "http://imdb.com/title/tt15399970"
    ],
    "language": "Íslenska",
    "image_urls": [
        "https://kvikmyndir.is/images/poster/gqtl0yocuxqdqzbfiz6ofa0yfdg-1669500619.jpg"
    ],
    "showtimes": [
        {
            "time": "2023-08-08T16:45:00",
            "cinema": "Bíó Paradís",
            "purchase_url": "https://tickets.bioparadis.is/#book/3096",
            "hall": "Salur 3",
            "tags": []
        }
    ],
    "trailer_url": "https://www.youtube.com/watch?v=KTFb6oODhy0",
    "images": [
        {
            "url": "https://kvikmyndir.is/images/poster/gqtl0yocuxqdqzbfiz6ofa0yfdg-1669500619.jpg",
            "path": "full/48b88c88382865ba0328036e6a3a50e9670b24bb.jpg",
            "checksum": "23d6afd9617fcbd0f5827f59d33f1656",
            "status": "downloaded"
        }
    ]
},
{
    "title": "Ofurljónið",
    "alt_title": "Just Super",
    "kvikmyndir_is_id": 16246,
    "release_year": 2022,
    "poster_url": "https://kvikmyndir.is/images/poster/1687812292688_ho00001632-1688653234.jpeg",
    "content_rating_in_years": 0,
    "scrape_url": "https://kvikmyndir.is/mynd/?id=16246",
    "description": "Líf hinnar ellefu ára gömlu tölvuleikjastelpu Hedvig breytist snögglega þegar hún neyðist til að leysa föður sinn af sem ofurhetja bæjarins, mun fyrr en búist var við. En Hedgvig er ekki ofurhetja og áskoranirnar eru mun meiri en faðir hennar bjóst við. Hann áttar sig fljótt á að hann þarf frekar að biðja íþróttastrákinn Adrian um að leysa verkefnið....",
    "genres": [
        "Fjölskylda",
        "Teiknað"
    ],
    "duration_in_mins": 76,
    "rating_urls": [
        "http://imdb.com/title/tt21212718"
    ],
    "language": "Norska",
    "image_urls": [
        "https://kvikmyndir.is/images/poster/1687812292688_ho00001632-1688653234.jpeg"
    ],
    "showtimes": [
        {
            "time": "2023-08-08T15:10:00",
            "cinema": "Laugarásbíó",
            "purchase_url": "http://kvikmyndahusio.azurewebsites.net/websales/show/769753/",
            "hall": "AXL",
            "tags": [
                "ÍSL TAL"
            ]
        }
    ],
    "trailer_url": "https://www.youtube.com/watch?v=5eIKTf10xPE",
    "images": [
        {
            "url": "https://kvikmyndir.is/images/poster/1687812292688_ho00001632-1688653234.jpeg",
            "path": "full/b559b0186c9b364170efac8230d9917a644eca66.jpg",
            "checksum": "1dbf6b4b90d0f14dc7197f19342ca7b3",
            "status": "downloaded"
        }
    ]
},
{
    "title": "Ruby Gillman, Teenage Kraken",
    "alt_title": "Ruby Gillman: Táningssæskrímslið",
    "kvikmyndir_is_id": 16100,
    "release_year": 2023,
    "poster_url": "https://kvikmyndir.is/images/poster/16100_500.jpg",
    "content_rating_in_years": 16,
    "scrape_url": "https://kvikmyndir.is/mynd/?id=16100",
    "description": "Hin sextán ára gamla Ruby Gillman kemst að því að hún tilheyrir goðsagnakenndri neðansjávar konungsfjölskyldu risasjóskrímsla. Örlög hennar breytast við þetta og verða meiri og stærri en hún gat nokkurn tímann gert sér í hugarlund.",
    "genres": [
        "Spenna",
        "Ævintýri",
        "Teiknað"
    ],
    "duration_in_mins": 90,
    "rating_urls": [
        "https://www.rottentomatoes.com/m/ruby_gillman_teenage_kraken",
        "http://imdb.com/title/tt27155038"
    ],
    "language": "Enska",
    "image_urls": [
        "https://kvikmyndir.is/images/poster/16100_500.jpg"
    ],
    "showtimes": [
        {
            "time": "2023-08-08T12:20:00",
            "cinema": "Sambíóin Kringlunni",
            "purchase_url": "http://www.sambio.is/websales/show/363725/",
            "hall": "Salur 2",
            "tags": [
                "ÍSL TAL"
            ]
        },
        {
            "time": "2023-08-08T13:00:00",
            "cinema": "Sambíóin Álfabakka",
            "purchase_url": "http://www.sambio.is/websales/show/363588/",
            "hall": "Salur 1",
            "tags": [
                "ÍSL TAL"
            ]
        },
        {
            "time": "2023-08-08T15:50:00",
            "cinema": "Laugarásbíó",
            "purchase_url": "http://kvikmyndahusio.azurewebsites.net/websales/show/769756/",
            "hall": "Salur A",
            "tags": [
                "ÍSL TAL"
            ]
        }
    ],
    "trailer_url": "https://www.youtube.com/watch?v=iAMKwDsfUeU",
    "images": [
        {
            "url": "https://kvikmyndir.is/images/poster/16100_500.jpg",
            "path": "full/6c311204eb14a6556d33b55b479d35b044a9912b.jpg",
            "checksum": "c40db0db309dc66b3c5b0a6a78bbe16c",
            "status": "downloaded"
        }
    ]
},
{
    "title": "Indiana Jones and the Dial of Destiny",
    "alt_title": "",
    "kvikmyndir_is_id": 15017,
    "release_year": 2023,
    "poster_url": "https://kvikmyndir.is/images/poster/1684983_500-1684746754.jpg",
    "content_rating_in_years": 12,
    "scrape_url": "https://kvikmyndir.is/mynd/?id=15017",
    "description": "Indinana Jones nálgast eftirlaunaaldur og reynir að passa inn í heim sem virðist vera orðinn honum framandi. En þegar gamall óvinur birtist þá þarf hetjan okkar að taka fram svipuna og hattinn til að koma í veg fyrir að fornir og kraftmiklir helgigripir lendi í röngum höndum.",
    "genres": [
        "Spenna",
        "Ævintýri"
    ],
    "duration_in_mins": 154,
    "rating_urls": [
        "https://www.rottentomatoes.com/m/indiana_jones_5",
        "http://imdb.com/title/tt1462764"
    ],
    "language": "Enska",
    "image_urls": [
        "https://kvikmyndir.is/images/poster/1684983_500-1684746754.jpg"
    ],
    "showtimes": [
        {
            "time": "2023-08-08T19:10:00",
            "cinema": "Sambíóin Álfabakka",
            "purchase_url": "http://www.sambio.is/websales/show/363615/",
            "hall": "Salur 3",
            "tags": []
        },
        {
            "time": "2023-08-08T22:20:00",
            "cinema": "Sambíóin Álfabakka",
            "purchase_url": "http://www.sambio.is/websales/show/363616/",
            "hall": "Salur 3",
            "tags": []
        }
    ],
    "trailer_url": "https://www.youtube.com/watch?v=ZfVYgWYaHmE",
    "images": [
        {
            "url": "https://kvikmyndir.is/images/poster/1684983_500-1684746754.jpg",
            "path": "full/4ba72971d167f45616699ae672be849a5dc1d7f8.jpg",
            "checksum": "f160f114068d15c137683adbe2fd9cb1",
            "status": "downloaded"
        }
    ]
},
{
    "title": "Elemental",
    "alt_title": "",
    "kvikmyndir_is_id": 15016,
    "release_year": 2023,
    "poster_url": "https://kvikmyndir.is/images/poster/15016_500.jpg",
    "content_rating_in_years": 0,
    "scrape_url": "https://kvikmyndir.is/mynd/?id=15016",
    "description": "Myndin fjallar um Ember og Wade í borg þar sem elds-, lands-, og loftsíbúar búa saman. Unga logandi heita konan og vatnsgaurinn, sem lætur sig fljóta með straumnum, eru um það bil að uppgötva hversu mikið þau eiga í raun sameiginlegt - þó að frumefni eins og þau eigi auðvitað ekki að geta blandast saman.",
    "genres": [
        "Gaman",
        "Ævintýri",
        "Teiknað"
    ],
    "duration_in_mins": 103,
    "rating_urls": [
        "http://imdb.com/title/tt15789038",
        "https://www.rottentomatoes.com/m/elemental_2023"
    ],
    "language": "Enska",
    "image_urls": [
        "https://kvikmyndir.is/images/poster/15016_500.jpg"
    ],
    "showtimes": [
        {
            "time": "2023-08-08T12:20:00",
            "cinema": "Sambíóin Kringlunni",
            "purchase_url": "http://www.sambio.is/websales/show/363694/",
            "hall": "Salur 3",
            "tags": [
                "ÍSL TAL"
            ]
        },
        {
            "time": "2023-08-08T14:20:00",
            "cinema": "Sambíóin Kringlunni",
            "purchase_url": "http://www.sambio.is/websales/show/363723/",
            "hall": "Salur 2",
            "tags": [
                "ÍSL TAL"
            ]
        },
        {
            "time": "2023-08-08T16:40:00",
            "cinema": "Sambíóin Kringlunni",
            "purchase_url": "http://www.sambio.is/websales/show/363724/",
            "hall": "Salur 2",
            "tags": [
                "ÍSL TAL"
            ]
        },
        {
            "time": "2023-08-08T12:50:00",
            "cinema": "Sambíóin Álfabakka",
            "purchase_url": "http://www.sambio.is/websales/show/363496/",
            "hall": "Salur A",
            "tags": [
                "ÍSL TAL"
            ]
        },
        {
            "time": "2023-08-08T15:00:00",
            "cinema": "Sambíóin Álfabakka",
            "purchase_url": "http://www.sambio.is/websales/show/363497/",
            "hall": "Salur A",
            "tags": [
                "ÍSL TAL"
            ]
        },
        {
            "time": "2023-08-08T13:00:00",
            "cinema": "Smárabíó",
            "purchase_url": "https://sala.smarabio.is/Ticketing/visSelectTickets.aspx?cinemacode=002&txtSessionId=100934&visLang=1",
            "hall": "Salur 5",
            "tags": [
                "ÍSL TAL"
            ]
        },
        {
            "time": "2023-08-08T15:20:00",
            "cinema": "Laugarásbíó",
            "purchase_url": "http://kvikmyndahusio.azurewebsites.net/websales/show/769759/",
            "hall": "Salur B",
            "tags": [
                "ÍSL TAL"
            ]
        }
    ],
    "trailer_url": "https://www.youtube.com/watch?v=hXzcyx9V0xw",
    "images": [
        {
            "url": "https://kvikmyndir.is/images/poster/15016_500.jpg",
            "path": "full/e98cfe7e6bb338dfc6feafd14ce3a8a1204ff3df.jpg",
            "checksum": "a9d9b32f13d4da2a41df1ec40cabad76",
            "status": "downloaded"
        }
    ]
},
{
    "title": "Haunted Mansion",
    "alt_title": "",
    "kvikmyndir_is_id": 16245,
    "release_year": 2023,
    "poster_url": "https://kvikmyndir.is/images/poster/1693199_500-1685874195.jpg",
    "content_rating_in_years": 12,
    "scrape_url": "https://kvikmyndir.is/mynd/?id=16245",
    "description": "Einstæð móðir að nafni Gabbie ræður leiðsögumann, miðil, prest og sagnfræðing til að hjálpa sér að særa illa anda út úr húsi sem hún er nýbúin að kaupa sér.",
    "genres": [
        "Gaman",
        "Drama",
        "Fjölskylda"
    ],
    "duration_in_mins": 123,
    "rating_urls": [
        "http://imdb.com/title/tt1695843",
        "https://www.rottentomatoes.com/m/haunted_mansion_2023"
    ],
    "language": "Enska",
    "image_urls": [
        "https://kvikmyndir.is/images/poster/1693199_500-1685874195.jpg"
    ],
    "showtimes": [
        {
            "time": "2023-08-08T13:50:00",
            "cinema": "Smárabíó",
            "purchase_url": "https://sala.smarabio.is/Ticketing/visSelectTickets.aspx?cinemacode=002&txtSessionId=101283&visLang=1",
            "hall": "Salur 4",
            "tags": []
        },
        {
            "time": "2023-08-08T16:40:00",
            "cinema": "Smárabíó",
            "purchase_url": "https://sala.smarabio.is/Ticketing/visSelectTickets.aspx?cinemacode=002&txtSessionId=100951&visLang=1",
            "hall": "Salur 4",
            "tags": []
        },
        {
            "time": "2023-08-08T19:30:00",
            "cinema": "Smárabíó",
            "purchase_url": "https://sala.smarabio.is/Ticketing/visSelectTickets.aspx?cinemacode=002&txtSessionId=100952&visLang=1",
            "hall": "Salur 4",
            "tags": []
        },
        {
            "time": "2023-08-08T22:20:00",
            "cinema": "Smárabíó",
            "purchase_url": "https://sala.smarabio.is/Ticketing/visSelectTickets.aspx?cinemacode=002&txtSessionId=100941&visLang=1",
            "hall": "Salur 5",
            "tags": []
        },
        {
            "time": "2023-08-08T14:20:00",
            "cinema": "Sambíóin Álfabakka",
            "purchase_url": "http://www.sambio.is/websales/show/363522/",
            "hall": "Salur B",
            "tags": []
        },
        {
            "time": "2023-08-08T17:00:00",
            "cinema": "Sambíóin Álfabakka",
            "purchase_url": "http://www.sambio.is/websales/show/363523/",
            "hall": "Salur B",
            "tags": []
        },
        {
            "time": "2023-08-08T19:40:00",
            "cinema": "Sambíóin Álfabakka",
            "purchase_url": "http://www.sambio.is/websales/show/363524/",
            "hall": "Salur B",
            "tags": []
        },
        {
            "time": "2023-08-08T22:20:00",
            "cinema": "Sambíóin Álfabakka",
            "purchase_url": "http://www.sambio.is/websales/show/363525/",
            "hall": "Salur B",
            "tags": []
        },
        {
            "time": "2023-08-08T15:00:00",
            "cinema": "Sambíóin Egilshöll",
            "purchase_url": "http://www.sambio.is/websales/show/363929/",
            "hall": "Salur 2",
            "tags": []
        },
        {
            "time": "2023-08-08T18:20:00",
            "cinema": "Sambíóin Egilshöll",
            "purchase_url": "http://www.sambio.is/websales/show/363936/",
            "hall": "Salur 3",
            "tags": []
        },
        {
            "time": "2023-08-08T17:00:00",
            "cinema": "Sambíóin Akureyri",
            "purchase_url": "http://www.sambio.is/websales/show/363964/",
            "hall": "Salur 2",
            "tags": []
        },
        {
            "time": "2023-08-08T17:30:00",
            "cinema": "Sambíóin Keflavík",
            "purchase_url": "http://www.sambio.is/websales/show/363266/",
            "hall": "Salur 2",
            "tags": []
        }
    ],
    "trailer_url": "https://www.youtube.com/watch?v=AjLKTz81bj8",
    "images": [
        {
            "url": "https://kvikmyndir.is/images/poster/1693199_500-1685874195.jpg",
            "path": "full/046157701cfe0e7799c7d7aa96ce1c00cfa812db.jpg",
            "checksum": "f65dae79b530f223bac2a763ac732bc6",
            "status": "downloaded"
        }
    ]
},
{
    "title": "Oppenheimer",
    "alt_title": "",
    "kvikmyndir_is_id": 14181,
    "release_year": 2023,
    "poster_url": "https://kvikmyndir.is/images/poster/1702120_500-1688982490.jpg",
    "content_rating_in_years": 12,
    "scrape_url": "https://kvikmyndir.is/mynd/?id=14181",
    "description": "Sagan af bandaríska vísindamanninum J. Robert Oppenheimer og þætti hans í þróun kjarnorkusprengjunnar.",
    "genres": [
        "Drama",
        "Söguleg",
        "Æviágrip"
    ],
    "duration_in_mins": 180,
    "rating_urls": [
        "https://www.rottentomatoes.com/m/oppenheimer_2023",
        "http://imdb.com/title/tt15398776"
    ],
    "language": "Enska",
    "image_urls": [
        "https://kvikmyndir.is/images/poster/1702120_500-1688982490.jpg"
    ],
    "showtimes": [
        {
            "time": "2023-08-08T15:00:00",
            "cinema": "Sambíóin Kringlunni",
            "purchase_url": "http://www.sambio.is/websales/show/364026/",
            "hall": "Ásberg",
            "tags": []
        },
        {
            "time": "2023-08-08T21:00:00",
            "cinema": "Sambíóin Kringlunni",
            "purchase_url": "http://www.sambio.is/websales/show/363668/",
            "hall": "Salur 1",
            "tags": []
        },
        {
            "time": "2023-08-08T15:30:00",
            "cinema": "Smárabíó",
            "purchase_url": "https://sala.smarabio.is/Ticketing/visSelectTickets.aspx?cinemacode=002&txtSessionId=101282&visLang=1",
            "hall": "Salur 5",
            "tags": []
        },
        {
            "time": "2023-08-08T20:00:00",
            "cinema": "Smárabíó",
            "purchase_url": "https://sala.smarabio.is/Ticketing/visSelectTickets.aspx?cinemacode=002&txtSessionId=100944&visLang=1",
            "hall": "Salur 2",
            "tags": []
        },
        {
            "time": "2023-08-08T21:30:00",
            "cinema": "Smárabíó",
            "purchase_url": "https://sala.smarabio.is/Ticketing/visSelectTickets.aspx?cinemacode=002&txtSessionId=100943&visLang=1",
            "hall": "LÚXUS",
            "tags": [
                "LÚX"
            ]
        },
        {
            "time": "2023-08-08T21:50:00",
            "cinema": "Smárabíó",
            "purchase_url": "https://sala.smarabio.is/Ticketing/visSelectTickets.aspx?cinemacode=002&txtSessionId=100942&visLang=1",
            "hall": "MAX",
            "tags": []
        },
        {
            "time": "2023-08-08T17:00:00",
            "cinema": "Laugarásbíó",
            "purchase_url": "http://kvikmyndahusio.azurewebsites.net/websales/show/769754/",
            "hall": "AXL",
            "tags": []
        },
        {
            "time": "2023-08-08T20:40:00",
            "cinema": "Laugarásbíó",
            "purchase_url": "http://kvikmyndahusio.azurewebsites.net/websales/show/769755/",
            "hall": "AXL",
            "tags": []
        },
        {
            "time": "2023-08-08T17:10:00",
            "cinema": "Sambíóin Álfabakka",
            "purchase_url": "http://www.sambio.is/websales/show/363494/",
            "hall": "Salur A",
            "tags": []
        },
        {
            "time": "2023-08-08T20:40:00",
            "cinema": "Sambíóin Álfabakka",
            "purchase_url": "http://www.sambio.is/websales/show/363495/",
            "hall": "Salur A",
            "tags": []
        },
        {
            "time": "2023-08-08T17:30:00",
            "cinema": "Sambíóin Egilshöll",
            "purchase_url": "http://www.sambio.is/websales/show/363927/",
            "hall": "Salur 2",
            "tags": []
        },
        {
            "time": "2023-08-08T21:00:00",
            "cinema": "Sambíóin Egilshöll",
            "purchase_url": "http://www.sambio.is/websales/show/363928/",
            "hall": "Salur 2",
            "tags": []
        },
        {
            "time": "2023-08-08T20:00:00",
            "cinema": "Sambíóin Keflavík",
            "purchase_url": "http://www.sambio.is/websales/show/363239/",
            "hall": "Salur 1",
            "tags": []
        },
        {
            "time": "2023-08-08T20:00:00",
            "cinema": "Sambíóin Akureyri",
            "purchase_url": "http://www.sambio.is/websales/show/363963/",
            "hall": "Salur 2",
            "tags": []
        }
    ],
    "trailer_url": "https://www.youtube.com/watch?v=bK6ldnjE3Y0",
    "images": [
        {
            "url": "https://kvikmyndir.is/images/poster/1702120_500-1688982490.jpg",
            "path": "full/abe9135f83065e8170e5ed1aad4dd0eca9ca91b5.jpg",
            "checksum": "c339088c1da8b817d73f6005c1699509",
            "status": "downloaded"
        }
    ]
},
{
    "title": "Meg 2: The Trench",
    "alt_title": "",
    "kvikmyndir_is_id": 16277,
    "release_year": 2023,
    "poster_url": "https://kvikmyndir.is/images/poster/16277_500.jpg",
    "content_rating_in_years": 12,
    "scrape_url": "https://kvikmyndir.is/mynd/?id=16277",
    "description": "Neðansjávarrannsóknarteymið fer ofaní myrkustu hyldýpi sjávar og berst þar við skelfilegar forsögulegar sjávarskepnur. Allt breytist þegar námuverkefni setur ferðina í uppnám. Nú þurfa þau á öllu sínu að halda til að lifa af.",
    "genres": [
        "Spenna",
        "Hrollvekja",
        "Ævintýri"
    ],
    "duration_in_mins": 116,
    "rating_urls": [
        "http://imdb.com/title/tt9224104",
        "https://www.rottentomatoes.com/m/meg_2_the_trench"
    ],
    "language": "Enska",
    "image_urls": [
        "https://kvikmyndir.is/images/poster/16277_500.jpg"
    ],
    "showtimes": [
        {
            "time": "2023-08-08T12:20:00",
            "cinema": "Sambíóin Kringlunni",
            "purchase_url": "http://www.sambio.is/websales/show/363748/",
            "hall": "Ásberg",
            "tags": []
        },
        {
            "time": "2023-08-08T19:00:00",
            "cinema": "Sambíóin Kringlunni",
            "purchase_url": "http://www.sambio.is/websales/show/363722/",
            "hall": "Salur 2",
            "tags": []
        },
        {
            "time": "2023-08-08T21:30:00",
            "cinema": "Sambíóin Kringlunni",
            "purchase_url": "http://www.sambio.is/websales/show/363693/",
            "hall": "Salur 3",
            "tags": []
        },
        {
            "time": "2023-08-08T22:00:00",
            "cinema": "Sambíóin Kringlunni",
            "purchase_url": "http://www.sambio.is/websales/show/363749/",
            "hall": "Ásberg",
            "tags": []
        },
        {
            "time": "2023-08-08T15:00:00",
            "cinema": "Sambíóin Egilshöll",
            "purchase_url": "http://www.sambio.is/websales/show/363942/",
            "hall": "Salur 4",
            "tags": []
        },
        {
            "time": "2023-08-08T21:00:00",
            "cinema": "Sambíóin Egilshöll",
            "purchase_url": "http://www.sambio.is/websales/show/363943/",
            "hall": "Salur 4",
            "tags": []
        },
        {
            "time": "2023-08-08T18:00:00",
            "cinema": "Laugarásbíó",
            "purchase_url": "http://kvikmyndahusio.azurewebsites.net/websales/show/769757/",
            "hall": "Salur A",
            "tags": []
        },
        {
            "time": "2023-08-08T20:30:00",
            "cinema": "Laugarásbíó",
            "purchase_url": "http://kvikmyndahusio.azurewebsites.net/websales/show/769758/",
            "hall": "Salur A",
            "tags": []
        },
        {
            "time": "2023-08-08T20:20:00",
            "cinema": "Sambíóin Keflavík",
            "purchase_url": "http://www.sambio.is/websales/show/363271/",
            "hall": "Salur 2",
            "tags": []
        }
    ],
    "trailer_url": "https://www.youtube.com/watch?v=dG91B3hHyY4",
    "images": [
        {
            "url": "https://kvikmyndir.is/images/poster/16277_500.jpg",
            "path": "full/af966025d6912860e0433d26a896cf5998540a5e.jpg",
            "checksum": "bfbc389d231c5da8ffc7f9ebb775a136",
            "status": "downloaded"
        }
    ]
}
]